link/__init__.py
link/dbrequest/__init__.py
link/dbrequest/assignment.py
link/dbrequest/ast.py
link/dbrequest/comparison.py
link/dbrequest/driver.py
link/dbrequest/expression.py
link/dbrequest/lazy.py
link/dbrequest/manager.py
link/dbrequest/model.py
link/dbrequest/query.py
link/dbrequest/tree.py
link/dbrequest/test/__init__.py
link/dbrequest/test/assignment.py
link/dbrequest/test/ast.py
link/dbrequest/test/comparison.py
link/dbrequest/test/driver.py
link/dbrequest/test/expression.py
link/dbrequest/test/lazy.py
link/dbrequest/test/manager.py
link/dbrequest/test/model.py
link/dbrequest/test/query.py
link/dbrequest/test/tree.py
link.dbrequest-0.19.dist-info/DESCRIPTION.rst
link.dbrequest-0.19.dist-info/METADATA
link.dbrequest-0.19.dist-info/RECORD
link.dbrequest-0.19.dist-info/WHEEL
link.dbrequest-0.19.dist-info/metadata.json
link.dbrequest-0.19.dist-info/top_level.txt
