Metadata-Version: 2.0
Name: link.dbrequest
Version: 0.19
Summary: Database agnostic query system
Home-page: https://github.com/linkdd/link.dbrequest
Author: David Delassus
Author-email: david.jose.delassus@gmail.com
License: MIT
Keywords: link database request
Platform: UNKNOWN
Classifier: Development Status :: 4 - Beta
Classifier: License :: OSI Approved :: MIT License
Classifier: Operating System :: OS Independent
Classifier: Topic :: Utilities
Classifier: Topic :: Software Development :: Libraries :: Python Modules
Classifier: Intended Audience :: Developers
Classifier: Programming Language :: Python
Classifier: Programming Language :: Python :: 2.7
Classifier: Programming Language :: Python :: 3
Classifier: Programming Language :: Python :: 3.4
Classifier: Programming Language :: Python :: 3.5
Classifier: Programming Language :: Python :: Implementation :: CPython
Requires-Dist: b3j0f.conf (>=0.3.19)
Requires-Dist: link.feature (>=2.1)
Requires-Dist: link.middleware (>=1.5)
Requires-Dist: mock (>=2.0.0)
Requires-Dist: six (>=1.10.0)
